bettercorrectfast/__init__.py
bettercorrectfast/bcf_two.py
bettercorrectfast/assets/icon.jpg
bettercorrectfast/assets/icon.png
bettercorrectfast/bcf/geometry.py
bettercorrectfast/bcf/inmemory_zipfile.py
bettercorrectfast/bcf/xml_parser.py
bettercorrectfast/bcf/agnostic/extensions.py
bettercorrectfast/bcf/v2/bcfxml.py
bettercorrectfast/bcf/v2/topic.py
bettercorrectfast/bcf/v2/visinfo.py
bettercorrectfast/bcf/v2/model/extensions.py
bettercorrectfast/bcf/v2/model/markup.py
bettercorrectfast/bcf/v2/model/project.py
bettercorrectfast/bcf/v2/model/version.py
bettercorrectfast/bcf/v2/model/visinfo.py
bettercorrectfast-0.2.0.dist-info/LICENSE
bettercorrectfast-0.2.0.dist-info/METADATA
bettercorrectfast-0.2.0.dist-info/WHEEL
bettercorrectfast-0.2.0.dist-info/top_level.txt
bettercorrectfast-0.2.0.dist-info/RECORD
