Metadata-Version: 2.1
Name: bettercorrectfast
Version: 0.2.0
Summary: Simplified BIM Collaboration Format (BCF) generation for project leaders and managers
Author-email: Boy d'Hont <contact@bdhont.net>
License: MIT
Requires-Python: >=3.10
License-File: LICENSE
Requires-Dist: xsdata
Requires-Dist: numpy
